pytest_mockservers/__init__.py
pytest_mockservers/http_server.py
pytest_mockservers/udp_server.py
pytest_mockservers-0.6.0.dist-info/entry_points.txt
pytest_mockservers-0.6.0.dist-info/LICENSE
pytest_mockservers-0.6.0.dist-info/WHEEL
pytest_mockservers-0.6.0.dist-info/METADATA
pytest_mockservers-0.6.0.dist-info/RECORD
