Metadata-Version: 2.1
Name: pytest-mockservers
Version: 0.6.0
Summary: A set of fixtures to test your requests to HTTP/UDP servers
Home-page: https://github.com/Gr1N/pytest-mockservers
License: MIT
Keywords: asyncio,pytest,plugin,http,upd,mock
Author: Nikita Grishko
Author-email: gr1n@protonmail.com
Requires-Python: >=3.6,<4.0
Classifier: License :: OSI Approved :: MIT License
Classifier: Programming Language :: Python :: 3
Classifier: Programming Language :: Python :: 3.6
Classifier: Programming Language :: Python :: 3.7
Classifier: Programming Language :: Python :: 3.8
Classifier: Topic :: Software Development :: Libraries :: Python Modules
Requires-Dist: aiohttp (>=3.0.0)
Requires-Dist: pytest (>=4.3.0)
Requires-Dist: pytest-asyncio (>=0.10.0)
Project-URL: Repository, https://github.com/Gr1N/pytest-mockservers
